hydlpy/__init__.py
hydlpy/model.py
hydlpy/criterion/__init__.py
hydlpy/criterion/base.py
hydlpy/criterion/kge_batch_loss.py
hydlpy/criterion/kge_norm_batch_loss.py
hydlpy/criterion/mse_loss.py
hydlpy/criterion/nse_batch_loss.py
hydlpy/criterion/nse_sqrt_batch_loss.py
hydlpy/criterion/range_bound_loss.py
hydlpy/criterion/rmse_comb_loss.py
hydlpy/criterion/rmse_loss.py
hydlpy/data/__init__.py
hydlpy/data/datamodule.py
hydlpy/data/dataset.py
hydlpy/estimators/__init__.py
hydlpy/estimators/base.py
hydlpy/estimators/implements/direct.py
hydlpy/estimators/implements/lstm.py
hydlpy/estimators/implements/mlp.py
hydlpy/hydrology/__init__.py
hydlpy/hydrology/hydrological_model.py
hydlpy/hydrology/hydrosymolic_model.py
hydlpy/hydrology/symbol_toolkit.py
hydlpy/hydrology/implements/__init__.py
hydlpy/hydrology/implements/exphydro.py
hydlpy/hydrology/implements/exphydro_manual.py
hydlpy/hydrology/implements/hbv.py
hydlpy/hydrology/implements/xaj.py
hydlpy/routing/__init__.py
hydlpy/routing/dmc.py
hydlpy/routing/route.py
hydlpy/utils/data.py
hydlpy/utils/factory.py
hydlpy/utils/metrics.py
hydlpy/utils/trainer.py
hydlpy-0.1.1.dist-info/METADATA
hydlpy-0.1.1.dist-info/WHEEL
hydlpy-0.1.1.dist-info/licenses/LICENSE
hydlpy-0.1.1.dist-info/RECORD
